droughty_dev/__init__.py
droughty_dev/config.py
droughty_dev/dbml_base_dict.py
droughty_dev/dbml_module.py
droughty_dev/dbt_test_base_dict.py
droughty_dev/dbt_test_cli.py
droughty_dev/dbt_test_module.py
droughty_dev/droughty_cli.py
droughty_dev/droughty_init.py
droughty_dev/droughty_init_cli.py
droughty_dev/lookml_base_dict.py
droughty_dev/lookml_cli.py
droughty_dev/lookml_module.py
droughty_dev/warehouse_target.py
droughty_dev-0.1.12.dist-info/entry_points.txt
droughty_dev-0.1.12.dist-info/WHEEL
droughty_dev-0.1.12.dist-info/METADATA
droughty_dev-0.1.12.dist-info/RECORD
