Metadata-Version: 2.1
Name: droughty-dev
Version: 0.1.12
Summary: 
License: MIT
Author: Lewis
Author-email: lewischarlesbaker@gmail.com
Requires-Python: >=3.9,<3.11
Classifier: License :: OSI Approved :: MIT License
Classifier: Programming Language :: Python :: 3
Classifier: Programming Language :: Python :: 3.10
Classifier: Programming Language :: Python :: 3.9
Requires-Dist: GitPython (==3.1.26)
Requires-Dist: PyYAML (==6.0)
Requires-Dist: SQLAlchemy (==1.4.22)
Requires-Dist: click (==8.0.1)
Requires-Dist: lkml (==1.1.0)
Requires-Dist: pandas (==1.3.1)
Requires-Dist: pandas-gbq (==0.15.0)
Requires-Dist: protobuf (==3.19.3)
Requires-Dist: pycryptodomex (==3.10.1)
Requires-Dist: ruamel.base (==1.0.0)
Requires-Dist: ruamel.yaml (>=0.17.20,<0.18.0)
Requires-Dist: snowflake (==0.0.3)
Requires-Dist: snowflake-connector-python (>=2.7.2,<3.0.0)
Requires-Dist: snowflake-sqlalchemy (>=1.3.3,<2.0.0)
